{
  "AP": "10",
  "GTS": "331",
  "PG": "1",
  "LST": "0830",
  "CC": "5",
  "CT": "9",
  "PRECIP": "7",
  "WS": "7",
  "WD": "5",
  "LAND_HAB": "41",
  "WATER_HAB": "00",
  "SAT_HOG": "10",
  "SAT_SUN": "140",
  "SAT_SHA": "134",
  "SWT": [
    "079",
    "122"
  ],
  "HYPRO": [
    "116",
    "110",
    "000",
    "000",
    "000"
  ],
  "STSL": [
    "135",
    "130",
    "129",
    "127",
    "127",
    "126"
  ],
  "STSH": [
    "112",
    "107",
    "104",
    "104",
    "102",
    "098"
  ],
  "SCDT": "1",
  "CST": "5",
  "STK": "0",
  "RBN": "4",
  "SHN": "0",
  "TDS": [
    "068",
    "291"
  ],
  "TUR": [
    "000",
    "000"
  ],
  "ALB": [
    "69",
    "94",
    "84",
    "88",
    "78",
    "37",
    "87",
    "83",
    "69",
    "99"
  ],
  "DELTA": "00",
  "WCD": [
    "00",
    "00",
    "00",
    "00",
    "00",
    "00",
    "00",
    "00",
    "00",
    "00"
  ],
  "WCV": [
    "00",
    "00",
    "00",
    "00",
    "00",
    "00",
    "00",
    "00",
    "00",
    "00"
  ],
  "WIDTH": [
    "000",
    "000"
  ],
  "IMG": [
    "0000",
    "0000",
    "0000",
    "0000",
    "0000",
    "0000",
    "0000",
    "0000",
    "0000",
    "0000",
    "0000",
    "0000",
    "0000",
    "0000"
  ],
  "PAN_IMGS": "00",
  "JOB": [
    "2",
    "5",
    "7",
    "8",
    "1",
    "7",
    "3",
    "1",
    "4",
    "1"
  ],
  "ROCK": {
    "SIM": "1",
    "AVG_SIZE": "10",
    "FW": "0",
    "FF": "0",
    "CVR": "0",
    "ERSN": "1",
    "SHP": "2",
    "B_FIELD": "80"
  },
  "TREE": [
    {
      "TREE_ID": "40",
      "TREE_PCT": "3",
      "TREE_DIA": "24",
      "TREE_HT": "14",
      "TREE_DEN": "10"
    },
    {
      "TREE_ID": "46",
      "TREE_PCT": "3",
      "TREE_DIA": "23",
      "TREE_HT": "14",
      "TREE_DEN": "04"
    }
  ],
  "BIRD": [
    {
      "BIRD_ID": "47",
      "BIRD_ACT": "0",
      "BIRD_LOC": "0",
      "BIRD_DIS": "2"
    },
    {
      "BIRD_ID": "39",
      "BIRD_ACT": "1",
      "BIRD_LOC": "3",
      "BIRD_DIS": "1"
    },
    {
      "BIRD_ID": "60",
      "BIRD_ACT": "0",
      "BIRD_LOC": "0",
      "BIRD_DIS": "2"
    }
  ],
  "MAMMAL": [],
  "DO": "N/A",
  "PH": "N/A",
  "N3": "N/A",
  "N2": "N/A",
  "NH": "N/A",
  "PO": "N/A",
  "CH": "N/A",
  "HD": "N/A",
  "AK": "N/A"
}