{
  "AP": "10",
  "GTS": "633",
  "PG": "1",
  "LST": "1145",
  "CC": "7",
  "CT": "9",
  "PCP": "0",
  "WS": "3",
  "WD": "5",
  "LAND_HAB": "41",
  "WATER_HAB": "00",
  "SAT_HOG": "10",
  "SAT_SUN": "172",
  "SAT_SHA": "160",
  "SWT": [
    "131",
    "134"
  ],
  "HYPRO": [
    "126",
    "000",
    "000",
    "000",
    "000"
  ],
  "STSL": [
    "141",
    "132",
    "124",
    "110",
    "095",
    "083"
  ],
  "STSH": [
    "129",
    "120",
    "113",
    "104",
    "091",
    "085"
  ],
  "SCDT": "1",
  "CST": "4",
  "STK": "3",
  "RBN": "4",
  "SHN": "1",
  "TDS": [
    "013",
    "105"
  ],
  "TUR": [
    "012",
    "020"
  ],
  "ALB": [
    "71",
    "44",
    "51",
    "69",
    "47",
    "79",
    "37",
    "16",
    "25",
    "39"
  ],
  "DELTA_X": "02",
  "WCD": [
    "01",
    "01",
    "02",
    "02",
    "02",
    "02",
    "02",
    "02",
    "03",
    "03"
  ],
  "WCV": [
    "00",
    "00",
    "00",
    "00",
    "00",
    "00",
    "00",
    "00",
    "00",
    "00"
  ],
  "WIDTH": [
    "010",
    "000"
  ],
  "IMG": [
    "2164",
    "2165",
    "2155",
    "2199",
    "2150",
    "2151",
    "2147",
    "2148",
    "2146",
    "2167",
    "2170",
    "2153",
    "2168",
    "2169"
  ],
  "NUMBER_IN_PAN": "09",
  "JOB": [
    "2",
    "9",
    "8",
    "7",
    "1",
    "5",
    "1",
    "7",
    "5",
    "4"
  ],
  "ROCKS": {
    "SIM": "2",
    "AVG_SIZE": "45",
    "FW": "0",
    "FF": "0",
    "CVR": "1",
    "ERSN": "1",
    "SHP": "5",
    "B_FIELD": "04"
  },
  "TREES": [
    {
      "ID": "25",
      "PCT": "1",
      "DIA": "30",
      "HT": "08",
      "DENSITY": "00"
    },
    {
      "ID": "50",
      "PCT": "2",
      "DIA": "15",
      "HT": "05",
      "DENSITY": "01"
    },
    {
      "ID": "32",
      "PCT": "1",
      "DIA": "99",
      "HT": "19",
      "DENSITY": "00"
    },
    {
      "ID": "45",
      "PCT": "1",
      "DIA": "07",
      "HT": "02",
      "DENSITY": "03"
    }
  ],
  "BIRDS": [
    {
      "ID": "86",
      "ACT": "0",
      "LOC": "0",
      "DIS": "2"
    },
    {
      "ID": "01",
      "ACT": "0",
      "LOC": "0",
      "DIS": "2"
    }
  ],
  "MAMMALS": [
    {
      "ID": "04",
      "ACT": "0",
      "LOC": "0",
      "EVD": "4"
    }
  ],
  "DO": "5.421",
  "PH": "9.03",
  "N3": "49.31",
  "N2": "16.85",
  "NH": "0.283",
  "PO": "0.321",
  "CH": "0.04",
  "HD": "103.2",
  "AK": "124.2",
  "SP": "N/A"
}