{"AP": ["11", "31"], "GTS": ["238", "416"], "PG": ["1", "1"], "LST": ["1535"], "CC": ["1"], "CT": ["3"], "PRECIP": ["0"], "WS": ["2"], "WD": ["7"], "LAND_HAB": ["41"], "WATER_HAB": [], "SAT_HOG": ["16"], "SAT_SUN": ["228"], "SAT_SHA": ["198"], "SWT": ["175", "173"], "HYPRO": ["152", "149", "147", "146", "146"], "STSL": ["200", "200", "184", "139", "131", "124"], "STSH": ["166", "155", "146", "124", "117", "116"], "SCDT": ["1"], "CST": ["2"], "STK": ["1"], "RBN": ["0"], "SHN": ["3"], "TDS": ["230", "220"], "TUR": ["@@3", "@@4"], "ALB": ["99", "99", "99", "99", "99", "99", "99", "99", "99", "99"], "DELTA": [], "WCD": [], "WCV": [], "WIDTH": [], "IMG": ["0648", "0646", "0672", "@638", "0643", "0645", "0639", "0640", "0637", "0649", "0650", "0652", "0641", "0642"], "PAN_IMGS": ["13"], "JOB": ["2", "7", "5", "2", "1", "8", "6", "3", "7"], "ROCK": [{"SIM": "@", "AVG_SIZE": "@@", "FW": "@", "FF": "@", "CVR": "1", "ERSN": "9", "SHP": "4", "B_FIELD": "@3"}], "TREE": [{"TREE_ID": "@2", "TREE_PCT": "@", "TREE_DIA": "15", "TREE_HT": "11", "TREE_DEN": "32"}, {"TREE_ID": "@@", "TREE_PCT": "@", "TREE_DIA": "@1", "TREE_HT": "41", "TREE_DEN": "32"}], "BIRD": [], "MAMMAL": [], "DO": "11.38", "PH": "6.00", "N3": "4.19", "N2": "0.17", "NH": "1.119", "PO": "0.705", "CH": "0.04", "HD": "10.45", "AK": "4.324", "SP": "6.045"}