{"AP": ["11"], "GTS": ["525"], "PG": ["1"], "LST": ["1540"], "CC": ["9"], "CT": ["3"], "PRECIP": ["0"], "WS": ["0"], "WD": ["0"], "LAND_HAB": ["41"], "WATER_HAB": [], "SAT_HOG": ["99"], "SAT_SUN": [], "SAT_SHA": ["151"], "SWT": [], "HYPRO": ["@00"], "STSL": ["151", "165", "149", "136", "121", "120"], "STSH": [], "SCDT": ["0"], "CST": ["2"], "STK": ["1"], "RBN": ["1"], "SHN": ["0"], "TDS": ["149", "153"], "TUR": [], "ALB": ["79", "88", "99", "99", "90", "87", "80", "99", "99", "99"], "DELTA": ["40"], "WCD": ["02", "04", "07", "07"], "WCV": [], "WIDTH": [], "IMG": ["4974", "4961", "4970", "4971", "4975", "4972", "4973", "4969", "4987", "4984", "4977", "4983", "4989"], "PAN_IMGS": ["@8"], "JOB": ["3", "8", "1", "4", "1", "2", "5", "4", "1"], "ROCK": [{"SIM": "@", "AVG_SIZE": "@@", "FW": "@", "FF": "@", "CVR": "4", "ERSN": "3", "SHP": "4", "B_FIELD": "10"}, {"SIM": "@", "AVG_SIZE": "@@", "FW": "@", "FF": "@", "CVR": "4", "ERSN": "6", "SHP": "3", "B_FIELD": "15"}], "TREE": [], "BIRD": [], "MAMMAL": [], "DO": "5.400", "PH": "N/A", "N3": "N/A", "N2": "N/A", "NH": "0.07", "PO": "0.07", "CH": "0.04", "HD": "N/A", "AK": "N/A", "SP": "N/A"}