{
  "AP": "11",
  "GTS": "635",
  "PG": "1",
  "LST": "1545",
  "CC": "3",
  "CT": "1",
  "PCP": "0",
  "WS": "6",
  "WD": "6",
  "LAND_HAB": "12",
  "WATER_HAB": "00",
  "SAT_HOG": "99",
  "SAT_SUN": "154",
  "SAT_SHA": "152",
  "SWT": [
    "121",
    "117"
  ],
  "HYPRO": [
    "123",
    "124",
    "121",
    "000",
    "000"
  ],
  "STSL": [
    "113",
    "106",
    "104",
    "101",
    "097",
    "083"
  ],
  "STSH": [
    "129",
    "121",
    "112",
    "104",
    "096",
    "088"
  ],
  "SCDT": "1",
  "CST": "2",
  "STK": "1",
  "RBN": "1",
  "SHN": "1",
  "TDS": [
    "192",
    "192"
  ],
  "TUR": [
    "010",
    "068"
  ],
  "ALB": [
    "93",
    "87",
    "51",
    "45",
    "90",
    "60",
    "34",
    "56",
    "63",
    "63"
  ],
  "DELTA_X": "00",
  "WCD": [
    "00",
    "00",
    "00",
    "00",
    "00",
    "00",
    "00",
    "00",
    "00",
    "00"
  ],
  "WCV": [
    "00",
    "00",
    "00",
    "00",
    "00",
    "00",
    "00",
    "00",
    "00",
    "00"
  ],
  "WIDTH": [
    "000",
    "000"
  ],
  "IMG": [
    "1569",
    "1568",
    "1558",
    "1573",
    "1574",
    "1566",
    "1571",
    "1572",
    "1567",
    "1582",
    "1583",
    "1578",
    "1581",
    "1580"
  ],
  "NUMBER_IN_PAN": "08",
  "JOB": [
    "2",
    "8",
    "3",
    "4",
    "7",
    "6",
    "5",
    "1",
    "9",
    "0"
  ],
  "ROCKS": {
    "SIM": "3",
    "AVG_SIZE": "99",
    "FW": "0",
    "FF": "0",
    "CVR": "0",
    "ERSN": "5",
    "SHP": "4",
    "B_FIELD": "04"
  },
  "TREES": [
    {
      "ID": "39",
      "PCT": "1",
      "DIA": "50",
      "HT": "27",
      "DENSITY": "20"
    },
    {
      "ID": "46",
      "PCT": "3",
      "DIA": "40",
      "HT": "35",
      "DENSITY": "10"
    },
    {
      "ID": "49",
      "PCT": "2",
      "DIA": "70",
      "HT": "32",
      "DENSITY": "15"
    }
  ],
  "BIRDS": [
    {
      "ID": "59",
      "ACT": "0",
      "LOC": "0",
      "DIS": "2"
    },
    {
      "ID": "47",
      "ACT": "0",
      "LOC": "0",
      "DIS": "2"
    },
    {
      "ID": "63",
      "ACT": "0",
      "LOC": "0",
      "DIS": "2"
    },
    {
      "ID": "50",
      "ACT": "0",
      "LOC": "0",
      "DIS": "2"
    }
  ],
  "MAMMALS": [
    {
      "ID": "01",
      "ACT": "0",
      "LOC": "0",
      "EVD": "5"
    },
    {
      "ID": "07",
      "ACT": "0",
      "LOC": "3",
      "EVD": "3"
    }
  ],
  "DO": "11.06",
  "PH": "7.039",
  "N3": "2.80",
  "N2": "0.569",
  "NH": "1.61",
  "PO": "7.90",
  "CH": "0.04",
  "HD": "42.59",
  "AK": "55.59",
  "SP": "4.579"
}