{
  "AP": "12",
  "GTS": "511",
  "PG": "1",
  "LST": "1440",
  "CC": "1",
  "CT": "2",
  "PRECIP": "0",
  "WS": "8",
  "WD": "2",
  "LAND_HAB": "54",
  "WATER_HAB": "00",
  "SAT_HOG": "10",
  "SAT_SUN": "231",
  "SAT_SHA": "228",
  "SWT": [
    "000",
    "000"
  ],
  "HYPRO": [
    "000",
    "000",
    "000",
    "000",
    "000"
  ],
  "STSL": [
    "000",
    "000",
    "000",
    "000",
    "000",
    "000"
  ],
  "STSH": [
    "000",
    "000",
    "000",
    "000",
    "000",
    "000"
  ],
  "SCDT": "0",
  "CST": "1",
  "STK": "1",
  "RBN": "2",
  "SHN": "1",
  "TDS": [
    "000",
    "000"
  ],
  "TUR": [
    "000",
    "000"
  ],
  "ALB": [
    "00",
    "00",
    "00",
    "00",
    "00",
    "00",
    "00",
    "00",
    "00",
    "00"
  ],
  "DELTA": "10",
  "WCD": [
    "01",
    "02",
    "03",
    "04",
    "05",
    "03",
    "06",
    "08",
    "08",
    "08"
  ],
  "WCV": [
    "01",
    "01",
    "01",
    "01",
    "01",
    "01",
    "01",
    "01",
    "01",
    "01"
  ],
  "WIDTH": [
    "100",
    "120"
  ],
  "IMG": [
    "0034",
    "0032",
    "0095",
    "0026",
    "0029",
    "0036",
    "0027",
    "0028",
    "0035",
    "0038",
    "0000",
    "0024",
    "0000",
    "0000"
  ],
  "PAN_IMGS": "19",
  "JOB": [
    "3",
    "1",
    "8",
    "4",
    "5",
    "2",
    "1",
    "8",
    "3",
    "1"
  ],
  "ROCK": [],
  "TREE": [],
  "BIRD": [
    {
      "BIRD_ID": "65",
      "BIRD_ACT": "0",
      "BIRD_LOC": "0",
      "BIRD_DIS": "2"
    },
    {
      "BIRD_ID": "82",
      "BIRD_ACT": "2",
      "BIRD_LOC": "4",
      "BIRD_DIS": "1"
    }
  ],
  "MAMMAL": [],
  "DO": "N/A",
  "PH": "N/A",
  "N3": "N/A",
  "N2": "N/A",
  "NH": "N/A",
  "PO": "N/A",
  "CH": "N/A",
  "HD": "N/A",
  "AK": "N/A"
}