{
  "AP": [
    "13",
    "13"
  ],
  "GTS": [
    "235",
    "235"
  ],
  "PG": [
    "1",
    "2"
  ],
  "LST": "1345",
  "CC": "5",
  "CT": "2",
  "PRECIP": "0",
  "WS": "2",
  "WD": "4",
  "LAND_HAB": "54",
  "WATER_HAB": "00",
  "SAT_HOG": "02",
  "SAT_SUN": "158",
  "SAT_SHA": "096",
  "SWT": [
    "123",
    "108"
  ],
  "HYPRO": [
    "125",
    "000",
    "000",
    "000",
    "000"
  ],
  "STSL": [
    "154",
    "153",
    "156",
    "157",
    "157",
    "158"
  ],
  "STSH": [
    "895",
    "097",
    "097",
    "099",
    "098",
    "100"
  ],
  "SCDT": "1",
  "CST": "4",
  "STK": "4",
  "RBN": "3",
  "SHN": "2",
  "TDS": [
    "204",
    "143"
  ],
  "TUR": [
    "023",
    "024"
  ],
  "ALB": [
    "99",
    "99",
    "99",
    "99",
    "99",
    "99",
    "99",
    "99",
    "99",
    "99"
  ],
  "DELTA": "03",
  "WCD": [
    "14",
    "25",
    "30",
    "44",
    "55",
    "58",
    "70",
    "86",
    "68",
    "60"
  ],
  "WCV": [
    "00",
    "00",
    "00",
    "00",
    "00",
    "00",
    "00",
    "00",
    "00",
    "00"
  ],
  "WIDTH": [
    "000",
    "000"
  ],
  "IMG": [
    "3835",
    "3836",
    "3819",
    "3834",
    "3833",
    "3832",
    "0000",
    "3837",
    "3831",
    "3845",
    "3846",
    "3840",
    "3840",
    "3839"
  ],
  "PAN_IMGS": "11",
  "JOB": [
    "7",
    "5",
    "8",
    "4",
    "1",
    "6",
    "5",
    "1",
    "1",
    "2"
  ],
  "ROCK": [],
  "TREE": [
    {
      "TREE_ID": "45",
      "TREE_PCT": "9",
      "TREE_DIA": "13",
      "TREE_HT": "04",
      "TREE_DEN": "30"
    }
  ],
  "BIRD": [
    {
      "BIRD_ID": "65",
      "BIRD_ACT": "1",
      "BIRD_LOC": "3",
      "BIRD_DIS": "2"
    },
    {
      "BIRD_ID": "59",
      "BIRD_ACT": "1",
      "BIRD_LOC": "3",
      "BIRD_DIS": "2"
    },
    {
      "BIRD_ID": "50",
      "BIRD_ACT": "1",
      "BIRD_LOC": "3",
      "BIRD_DIS": "2"
    }
  ],
  "MAMMAL": [
    {
      "MML_ID": "04",
      "MML_ACT": "4",
      "MML_LOC": "4",
      "MML_EVD": "4"
    }
  ],
  "DO": "2.190",
  "PH": "5.94",
  "N3": "6.84",
  "N2": "0.10",
  "NH": "0.600",
  "PO": "4.05",
  "CH": "0.105",
  "HD": "659.9",
  "AK": "17.82",
  "SP": "7.31"
}