{
  "AP": [
    "13",
    "13"
  ],
  "GTS": [
    "326",
    "326"
  ],
  "PG": [
    "1",
    "2"
  ],
  "LST": "1506",
  "CC": "9",
  "CT": "1",
  "PCP": "1",
  "WS": "0",
  "WD": "0",
  "LAND_HAB": "41",
  "WATER_HAB": "00",
  "SAT_HOG": "30",
  "SAT_SUN": "000",
  "SAT_SHA": "117",
  "SWT": [
    "160",
    "158"
  ],
  "HYPRO": [
    "157",
    "151",
    "147",
    "000",
    "000"
  ],
  "STSL": [
    "000",
    "000",
    "000",
    "000",
    "000",
    "000"
  ],
  "STSH": [
    "107",
    "113",
    "112",
    "105",
    "098",
    "094"
  ],
  "SCDT": "1",
  "CST": "3",
  "STK": "2",
  "RBN": "2",
  "SHN": "0",
  "TDS": [
    "080",
    "082"
  ],
  "TUR": [
    "056",
    "000"
  ],
  "ALB": [
    "06",
    "05",
    "08",
    "09",
    "12",
    "15",
    "18",
    "17",
    "18",
    "22"
  ],
  "DELTA_X": "05",
  "WCD": [
    "05",
    "06",
    "06",
    "08",
    "09",
    "06",
    "07",
    "07",
    "08",
    "10"
  ],
  "WCV": [
    "00",
    "00",
    "00",
    "00",
    "00",
    "00",
    "00",
    "00",
    "00",
    "00"
  ],
  "WIDTH": [
    "000",
    "000"
  ],
  "IMG": [
    "2890",
    "2872",
    "2850",
    "2861",
    "2862",
    "2863",
    "2879",
    "2864",
    "2860",
    "2876",
    "2875",
    "2869",
    "2878",
    "2877"
  ],
  "NUMBER_IN_PAN": "10",
  "JOB": [
    "1",
    "1",
    "4",
    "5",
    "5",
    "7",
    "1",
    "2",
    "1",
    "8"
  ],
  "ROCKS": [
    {
      "SIM": "3",
      "AVG_SIZE": "30",
      "FW": "0",
      "FF": "0",
      "CVR": "0",
      "ERSN": "2",
      "SHP": "2",
      "B_FIELD": "00"
    }
  ],
  "TREES": [
    {
      "ID": "48",
      "PCT": "4",
      "DIA": "46",
      "HT": "09",
      "DENSITY": "04"
    },
    {
      "ID": "49",
      "PCT": "4",
      "DIA": "99",
      "HT": "18",
      "DENSITY": "05"
    },
    {
      "ID": "39",
      "PCT": "2",
      "DIA": "99",
      "HT": "21",
      "DENSITY": "00"
    }
  ],
  "BIRDS": [
    {
      "ID": "81",
      "ACT": "0",
      "LOC": "0",
      "DIS": "2"
    },
    {
      "ID": "74",
      "ACT": "0",
      "LOC": "0",
      "DIS": "2"
    }
  ],
  "MAMMALS": [
    {
      "ID": "08",
      "ACT": "0",
      "LOC": "0",
      "EVD": "1"
    }
  ],
  "DO": "2.063",
  "PH": "7.629",
  "N3": "7.586",
  "N2": "0.741",
  "NH": "2.875",
  "PO": "3.81",
  "CH": "0.013",
  "HD": "11.82",
  "AK": "250.5",
  "SP": "6.133"
}