{
  "AP": [
    "13",
    "13"
  ],
  "GTS": [
    "411",
    "411"
  ],
  "PG": [
    "1",
    "2"
  ],
  "LST": "1400",
  "CC": "9",
  "CT": "3",
  "PRECIP": "0",
  "WS": "0",
  "WD": "0",
  "LAND_HAB": "44",
  "WATER_HAB": "00",
  "SAT_HOG": "03",
  "SAT_SUN": "000",
  "SAT_SHA": "150",
  "SWT": [
    "142",
    "000"
  ],
  "HYPRO": [
    "138",
    "135",
    "132",
    "000",
    "000"
  ],
  "STSL": [
    "000",
    "000",
    "000",
    "000",
    "000",
    "000"
  ],
  "STSH": [
    "142",
    "139",
    "137",
    "134",
    "131",
    "131"
  ],
  "SCDT": "2",
  "CST": "3",
  "STK": "3",
  "RBN": "3",
  "SHN": "0",
  "TDS": [
    "000",
    "000"
  ],
  "TUR": [
    "006",
    "000"
  ],
  "ALB": [
    "23",
    "19",
    "15",
    "19",
    "13",
    "17",
    "27",
    "48",
    "11",
    "29"
  ],
  "DELTA": "01",
  "WCD": [
    "01",
    "03",
    "04",
    "04",
    "05",
    "00",
    "00",
    "00",
    "00",
    "00"
  ],
  "WCV": [
    "01",
    "01",
    "02",
    "02",
    "02",
    "00",
    "00",
    "00",
    "00",
    "00"
  ],
  "WIDTH": [
    "015",
    "000"
  ],
  "IMG": [
    "0025",
    "0026",
    "0010",
    "0021",
    "0022",
    "0027",
    "0023",
    "0024",
    "0028",
    "0035",
    "0032",
    "0037",
    "0036",
    "0030"
  ],
  "PAN_IMGS": "10",
  "JOB": [
    "4",
    "5",
    "1",
    "6",
    "3",
    "1",
    "7",
    "9",
    "4",
    "2"
  ],
  "ROCK": [
    {
      "SIM": "3",
      "AVG_SIZE": "60",
      "FW": "2",
      "FF": "6",
      "CVR": "1",
      "ERSN": "1",
      "SHP": "5",
      "B_FIELD": "20"
    },
    {
      "SIM": "2",
      "AVG_SIZE": "40",
      "FW": "0",
      "FF": "0",
      "CVR": "0",
      "ERSN": "1",
      "SHP": "6",
      "B_FIELD": "18"
    }
  ],
  "TREE": [
    {
      "TREE_ID": "45",
      "TREE_PCT": "2",
      "TREE_DIA": "20",
      "TREE_HT": "14",
      "TREE_DEN": "05"
    },
    {
      "TREE_ID": "47",
      "TREE_PCT": "3",
      "TREE_DIA": "08",
      "TREE_HT": "05",
      "TREE_DEN": "06"
    },
    {
      "TREE_ID": "46",
      "TREE_PCT": "3",
      "TREE_DIA": "15",
      "TREE_HT": "16",
      "TREE_DEN": "04"
    },
    {
      "TREE_ID": "48",
      "TREE_PCT": "2",
      "TREE_DIA": "20",
      "TREE_HT": "13",
      "TREE_DEN": "04"
    }
  ],
  "BIRD": [
    {
      "BIRD_ID": "47",
      "BIRD_ACT": "0",
      "BIRD_LOC": "0",
      "BIRD_DIS": "2"
    },
    {
      "BIRD_ID": "60",
      "BIRD_ACT": "0",
      "BIRD_LOC": "0",
      "BIRD_DIS": "2"
    },
    {
      "BIRD_ID": "81",
      "BIRD_ACT": "0",
      "BIRD_LOC": "0",
      "BIRD_DIS": "2"
    }
  ],
  "MAMMAL": [
    {
      "MML_ID": "01",
      "MML_ACT": "4",
      "MML_LOC": "3",
      "MML_EVD": "4"
    },
    {
      "MML_ID": "04",
      "MML_ACT": "4",
      "MML_LOC": "3",
      "MML_EVD": "4"
    }
  ],
  "DO": "N/A",
  "PH": "N/A",
  "N3": "N/A",
  "N2": "N/A",
  "NH": "N/A",
  "PO": "N/A",
  "CH": "N/A",
  "HD": "N/A",
  "AK": "N/A",
  "SP": "N/A"
}