{"AP": ["14", "14"], "GTS": ["223", "223"], "PG": ["1", "2"], "LST": ["1227"], "CC": ["6"], "CT": ["1"], "PRECIP": ["0"], "WS": ["0"], "WD": ["0"], "LAND_HAB": ["44"], "WATER_HAB": ["00"], "SAT_HOG": ["00"], "SAT_SUN": ["000"], "SAT_SHA": ["000"], "SWT": ["000", "000"], "HYPRO": ["000", "000", "000", "000", "000"], "STSL": ["000", "000", "000", "000", "000", "000"], "STSH": ["000", "000", "000", "000", "000", "000"], "SCDT": ["1"], "CST": ["2"], "STK": ["1"], "RBN": ["1"], "SHN": ["1"], "TDS": ["000", "000"], "TUR": ["000", "000"], "ALB": ["00", "00", "00", "00", "00", "00", "00", "00", "00", "00"], "DELTA": ["00"], "WCD": ["01", "00", "00", "00", "00", "00", "00", "00", "00", "00"], "WCV": ["01", "00", "00", "00", "00", "00", "00", "00", "00", "00"], "WIDTH": ["005", "015"], "IMG": ["0321", "0318", "0303", "0322", "0323", "0315", "0324", "0325", "0330", "0319", "0316", "0331", "0312", "0000"], "PAN_IMGS": ["09"], "JOB": ["9", "7", "1", "2", "8", "5", "3", "6", "4", "0"], "ROCK": [{"SIM": "2", "AVG_SIZE": "22", "FW": "0", "FF": "0", "CVR": "1", "ERSN": "2", "SHP": "5", "B_FIELD": "00"}], "TREE": [{"TREE_ID": "43", "TREE_PCT": "8", "TREE_DIA": "50", "TREE_HT": "30", "TREE_DEN": "03"}, {"TREE_ID": "31", "TREE_PCT": "1", "TREE_DIA": "43", "TREE_HT": "17", "TREE_DEN": "09"}], "BIRD": [{"BIRD_ID": "65", "BIRD_ACT": "0", "BIRD_LOC": "0", "BIRD_DIS": "2"}, {"BIRD_ID": "42", "BIRD_ACT": "1", "BIRD_LOC": "3", "BIRD_DIS": "2"}, {"BIRD_ID": "80", "BIRD_ACT": "0", "BIRD_LOC": "0", "BIRD_DIS": "2"}, {"BIRD_ID": "26", "BIRD_ACT": "2", "BIRD_LOC": "4", "BIRD_DIS": "1"}, {"BIRD_ID": "50", "BIRD_ACT": "0", "BIRD_LOC": "0", "BIRD_DIS": "2"}], "MAMMAL": [], "DO": "11.07", "PH": "5.577", "N3": "27.17", "N2": "0.25", "NH": "1.158", "PO": "3.95", "CH": "N/A", "HD": "12.07", "AK": "17.67", "SP": "6.234"}