{"AP": ["14", "14"], "GTS": ["531", "531"], "PG": ["1", "2"], "LST": ["1047"], "CC": ["6"], "CT": ["1"], "PRECIP": ["0"], "WS": ["0"], "WD": ["0"], "LAND_HAB": ["43"], "WATER_HAB": ["00"], "SAT_HOG": ["12"], "SAT_SUN": ["223"], "SAT_SHA": ["211"], "SWT": ["181", "183"], "HYPRO": ["180", "182", "000", "000", "000"], "STSL": ["235", "202", "160", "147", "132", "122"], "STSH": ["175", "165", "144", "130", "126", "118"], "SCDT": ["1"], "CST": ["3"], "STK": ["2"], "RBN": ["2"], "SHN": ["0"], "TDS": ["076", "082"], "TUR": ["007", "008"], "ALB": ["09", "09", "09", "09", "09", "09", "09", "09", "09", "09"], "DELTA": ["02"], "WCD": ["01", "01", "01", "01", "01", "00", "00", "00", "00", "00"], "WCV": ["02", "01", "00", "00", "00", "00", "00", "00", "00", "00"], "WIDTH": ["028", "025"], "IMG": ["0571", "0582", "0561", "0573", "0574", "0579", "0575", "0576", "0577", "0587", "0586", "0580", "0585", "0000"], "PAN_IMGS": ["09"], "JOB": ["2", "1", "5", "3", "2", "8", "0", "5", "1", "4"], "ROCK": [{"SIM": "2", "AVG_SIZE": "60", "FW": "0", "FF": "0", "CVR": "0", "ERSN": "1", "SHP": "1", "B_FIELD": "16"}], "TREE": [{"TREE_ID": "43", "TREE_PCT": "9", "TREE_DIA": "36", "TREE_HT": "16", "TREE_DEN": "04"}], "BIRD": [{"BIRD_ID": "59", "BIRD_ACT": "0", "BIRD_LOC": "0", "BIRD_DIS": "2"}, {"BIRD_ID": "80", "BIRD_ACT": "0", "BIRD_LOC": "0", "BIRD_DIS": "2"}, {"BIRD_ID": "81", "BIRD_ACT": "0", "BIRD_LOC": "0", "BIRD_DIS": "2"}, {"BIRD_ID": "57", "BIRD_ACT": "0", "BIRD_LOC": "0", "BIRD_DIS": "2"}, {"BIRD_ID": "75", "BIRD_ACT": "0", "BIRD_LOC": "0", "BIRD_DIS": "2"}, {"BIRD_ID": "65", "BIRD_ACT": "0", "BIRD_LOC": "0", "BIRD_DIS": "2"}], "MAMMAL": [], "DO": "5.571", "PH": "24.06", "N3": "0.641", "N2": "2.111", "NH": "0.646", "PO": "N/A", "CH": "11.94", "HD": "42.22", "AK": "6.506"}