{
  "AP": [
    "15",
    "15"
  ],
  "GTS": [
    "322",
    "322"
  ],
  "PG": [
    "1",
    "2"
  ],
  "LST": "0930",
  "CC": "9",
  "CT": "3",
  "PRECIP": "0",
  "WS": "0",
  "WD": "0",
  "LAND_HAB": "00",
  "WATER_HAB": "41",
  "SAT_HOG": "90",
  "SAT_SUN": "000",
  "SAT_SHA": "108",
  "SWT": [
    "129",
    "129"
  ],
  "HYPRO": [
    "127",
    "129",
    "000",
    "000",
    "000"
  ],
  "STSL": [
    "000",
    "000",
    "000",
    "000",
    "000",
    "000"
  ],
  "STSH": [
    "109",
    "094",
    "081",
    "066",
    "056",
    "048"
  ],
  "SCDT": "2",
  "CST": "1",
  "STK": "0",
  "RBN": "0",
  "SHN": "0",
  "TDS": [
    "342",
    "335"
  ],
  "TUR": [
    "000",
    "000"
  ],
  "ALB": [
    "09",
    "10",
    "10",
    "08",
    "09",
    "09",
    "08",
    "10",
    "09",
    "10"
  ],
  "DELTA": "00",
  "WCD": [
    "00",
    "00",
    "00",
    "00",
    "00",
    "00",
    "00",
    "00",
    "00",
    "00"
  ],
  "WCV": [
    "00",
    "00",
    "00",
    "00",
    "00",
    "00",
    "00",
    "00",
    "00",
    "00"
  ],
  "WIDTH": [
    "000",
    "000"
  ],
  "IMG": [
    "0000",
    "0000",
    "4067",
    "4011",
    "4072",
    "4066",
    "4081",
    "4070",
    "4069",
    "4077",
    "4080",
    "4075",
    "4079",
    "0000"
  ],
  "PAN_IMGS": "09",
  "JOB": [
    "2",
    "4",
    "6",
    "3",
    "8",
    "5",
    "1",
    "1",
    "7",
    "0"
  ],
  "ROCK": [
    {
      "SIM": "3",
      "AVG_SIZE": "52",
      "FW": "0",
      "FF": "0",
      "CVR": "1",
      "ERSN": "1",
      "SHP": "2",
      "B_FIELD": "04"
    }
  ],
  "TREE": [
    {
      "TREE_ID": "49",
      "TREE_PCT": "2",
      "TREE_DIA": "62",
      "TREE_HT": "27",
      "TREE_DEN": "07"
    },
    {
      "TREE_ID": "43",
      "TREE_PCT": "7",
      "TREE_DIA": "20",
      "TREE_HT": "12",
      "TREE_DEN": "02"
    },
    {
      "TREE_ID": "13",
      "TREE_PCT": "1",
      "TREE_DIA": "50",
      "TREE_HT": "27",
      "TREE_DEN": "03"
    }
  ],
  "BIRD": [
    {
      "BIRD_ID": "09",
      "BIRD_ACT": "0",
      "BIRD_LOC": "1",
      "BIRD_DIS": "4"
    },
    {
      "BIRD_ID": "11",
      "BIRD_ACT": "0",
      "BIRD_LOC": "1",
      "BIRD_DIS": "3"
    },
    {
      "BIRD_ID": "37",
      "BIRD_ACT": "0",
      "BIRD_LOC": "3",
      "BIRD_DIS": "2"
    },
    {
      "BIRD_ID": "81",
      "BIRD_ACT": "0",
      "BIRD_LOC": "0",
      "BIRD_DIS": "2"
    }
  ],
  "MAMMAL": [
    {
      "MML_ID": "14",
      "MML_ACT": "0",
      "MML_LOC": "0",
      "MML_EVD": "7"
    },
    {
      "MML_ID": "08",
      "MML_ACT": "0",
      "MML_LOC": "0",
      "MML_EVD": "1"
    }
  ],
  "DO": "6.536",
  "PH": "28.71",
  "N3": "1.630",
  "N2": "2.905",
  "NH": "0.580",
  "PO": "N/A",
  "CH": "4.167",
  "HD": "13.33",
  "AK": "5.508"
}