{
  "AP": [
    "15",
    "15"
  ],
  "GTS": [
    "332",
    "332"
  ],
  "PG": [
    "1",
    "2"
  ],
  "LST": "0925",
  "CC": "9",
  "CT": "3",
  "PCP": "0",
  "WS": "0",
  "WD": "0",
  "LAND_HAB": "00",
  "WATER_HAB": "41",
  "SAT_HOG": "80",
  "SAT_SUN": "000",
  "SAT_SHA": "210",
  "SWT": [
    "141",
    "138"
  ],
  "HYPRO": [
    "138",
    "136",
    "000",
    "000",
    "000"
  ],
  "STSL": [
    "000",
    "000",
    "000",
    "000",
    "000",
    "000"
  ],
  "STSH": [
    "160",
    "152",
    "145",
    "141",
    "137",
    "133"
  ],
  "SCDT": "2",
  "CST": "0",
  "STK": "0",
  "RBN": "0",
  "SHN": "0",
  "TDS": [
    "072",
    "021"
  ],
  "TUR": [
    "004",
    "006"
  ],
  "ALB": [
    "26",
    "26",
    "24",
    "23",
    "19",
    "14",
    "12",
    "14",
    "18",
    "21"
  ],
  "DELTA_X": "00",
  "WCD": [
    "00",
    "00",
    "00",
    "00",
    "00",
    "00",
    "00",
    "00",
    "00",
    "00"
  ],
  "WCV": [
    "00",
    "00",
    "00",
    "00",
    "00",
    "00",
    "00",
    "00",
    "00",
    "00"
  ],
  "WIDTH": [
    "000",
    "000"
  ],
  "IMG": [
    "4275",
    "4276",
    "4255",
    "0000",
    "4273",
    "4274",
    "4268",
    "4272",
    "4267",
    "4278",
    "4284",
    "4281",
    "4280",
    "0000"
  ],
  "NUMBER_IN_PAN": "12",
  "JOB": [
    "2",
    "4",
    "6",
    "3",
    "8",
    "6",
    "1",
    "1",
    "7",
    "0"
  ],
  "ROCKS": [
    {
      "SIM": "3",
      "AVG_SIZE": "05",
      "FW": "0",
      "FF": "0",
      "CVR": "0",
      "ERSN": "1",
      "SHP": "2",
      "B_FIELD": "07"
    }
  ],
  "TREES": [
    {
      "ID": "39",
      "PCT": "9",
      "DIA": "66",
      "HT": "21",
      "DENSITY": "01"
    },
    {
      "ID": "46",
      "PCT": "1",
      "DIA": "05",
      "HT": "03",
      "DENSITY": "05"
    }
  ],
  "BIRDS": [
    {
      "ID": "50",
      "ACT": "0",
      "LOC": "0",
      "DIS": "2"
    },
    {
      "ID": "37",
      "ACT": "0",
      "LOC": "3",
      "DIS": "2"
    },
    {
      "ID": "81",
      "ACT": "0",
      "LOC": "0",
      "DIS": "2"
    }
  ],
  "MAMMALS": [],
  "DO": "7.000",
  "PH": "9.02",
  "N3": "122.1",
  "N2": "5.962",
  "NH": "1.436",
  "PO": "0.350",
  "CH": "N/A",
  "HD": "549.6",
  "AK": "141.8",
  "SP": "4.676"
}