{
  "AP": [
    "16",
    "16"
  ],
  "GTS": [
    "624",
    "624"
  ],
  "PG": "1",
  "LST": [
    "1200"
  ],
  "CC": "0",
  "CT": "0",
  "PRECIP": "0",
  "WS": "0",
  "WD": "0",
  "LAND_HAB": [
    "12"
  ],
  "WATER_HAB": [
    "43"
  ],
  "SAT_HOG": [
    "12"
  ],
  "SAT_SUN": [
    "195"
  ],
  "SAT_SHA": [
    "123"
  ],
  "SWT": [
    "071",
    "076"
  ],
  "HYPRO": [
    "067",
    "060",
    "066",
    "000",
    "000"
  ],
  "STSL": [
    "118",
    "107",
    "103",
    "096",
    "097",
    "097"
  ],
  "STSH": [
    "102",
    "097",
    "094",
    "095",
    "100",
    "097"
  ],
  "SCDT": "2",
  "CST": "2",
  "STK": "3",
  "RBN": "2",
  "SHN": "1",
  "TDS": [
    "000",
    "000"
  ],
  "TUR": [
    "000",
    "000"
  ],
  "ALB": [
    "04",
    "10",
    "10",
    "10",
    "04",
    "10",
    "04",
    "10",
    "10",
    "03"
  ],
  "DELTA": [
    "05"
  ],
  "WCD": [
    "11",
    "01",
    "12",
    "02",
    "04",
    "03",
    "05",
    "00",
    "06",
    "06"
  ],
  "WCV": [
    "12",
    "11",
    "11",
    "10",
    "12",
    "12",
    "11",
    "10",
    "12",
    "12"
  ],
  "WIDTH": [
    "217",
    "023"
  ],
  "IMG": [
    "0296",
    "0297",
    "0282",
    "0303",
    "0305",
    "0095",
    "0299",
    "0300",
    "0298",
    "0310",
    "0015",
    "0301",
    "0300",
    "0000"
  ],
  "PAN_IMGS": [
    "11"
  ],
  "JOB": "1",
  "ROCK": [
    {
      "SIM": "0",
      "AVG_SIZE": "00",
      "FW": "4",
      "FF": "8",
      "CVR": "0",
      "ERSN": "1",
      "SHP": "0",
      "B_FIELD": "35"
    }
  ],
  "TREE": [
    {
      "TREE_ID": "49",
      "TREE_PCT": "9",
      "TREE_DIA": "10",
      "TREE_HT": "18",
      "TREE_DEN": "01"
    },
    {
      "TREE_ID": "31",
      "TREE_PCT": "7",
      "TREE_DIA": "10",
      "TREE_HT": "20",
      "TREE_DEN": "20"
    }
  ],
  "BIRD": [
    {
      "BIRD_ID": "19",
      "BIRD_ACT": "5",
      "BIRD_LOC": "5",
      "BIRD_DIS": "1"
    }
  ],
  "MAMMAL": [
    {
      "MML_ID": "04",
      "MML_ACT": "0",
      "MML_LOC": "6",
      "MML_EVD": "4"
    }
  ],
  "DO": "N/A",
  "PH": "N/A",
  "N3": "N/A",
  "N2": "N/A",
  "NH": "N/A",
  "PO": "N/A",
  "CH": "N/A",
  "HD": "N/A",
  "AK": "N/A"
}