{"AP": ["19", "19"], "GTS": ["302", "302"], "PG": ["1", "2"], "LST": ["1725"], "CC": ["0"], "CT": ["0"], "PRECIP": ["0"], "WS": ["0"], "WD": ["0"], "LAND_HAB": ["43"], "WATER_HAB": ["00"], "SAT_HOG": ["00"], "SAT_SUN": ["136"], "SAT_SHA": ["133"], "SWT": ["123", "125"], "HYPRO": ["117", "113", "113", "111", "111"], "STSL": ["123", "107", "099", "084", "077", "000"], "STSH": ["000", "000", "000", "000", "000", "000"], "SCDT": ["1"], "CST": ["4"], "STK": ["3"], "RBN": ["3"], "SHN": ["2"], "TDS": ["590", "590"], "TUR": ["388", "133"], "ALB": ["00", "00", "00", "00", "00", "00", "00", "00", "00", "00"], "DELTA": ["10"], "WCD": ["01", "01", "01", "01", "01", "01", "01", "01", "01", "01"], "WCV": ["04", "06", "08", "13", "14", "10", "13", "13", "16", "19"], "WIDTH": ["000", "000"], "IMG": ["0000", "0000", "0000", "3235", "3237", "3239", "3241", "9242", "3240", "3243", "3244", "3247", "3245", "3246"], "PAN_IMGS": ["00"], "JOB": ["0", "5", "4", "7", "1", "0", "0", "1", "2", "0"], "ROCK": [{"SIM": "2", "AVG_SIZE": "30", "FW": "5", "FF": "1", "CVR": "3", "ERSN": "1", "SHP": "0", "B_FIELD": "00"}, {"SIM": "1", "AVG_SIZE": "20", "FW": "5", "FF": "1", "CVR": "3", "ERSN": "2", "SHP": "2", "B_FIELD": "00"}], "TREE": [{"TREE_ID": "50", "TREE_PCT": "4", "TREE_DIA": "90", "TREE_HT": "19", "TREE_DEN": "17"}, {"TREE_ID": "40", "TREE_PCT": "4", "TREE_DIA": "30", "TREE_HT": "10", "TREE_DEN": "09"}, {"TREE_ID": "18", "TREE_PCT": "1", "TREE_DIA": "13", "TREE_HT": "07", "TREE_DEN": "04"}, {"TREE_ID": "31", "TREE_PCT": "1", "TREE_DIA": "30", "TREE_HT": "13", "TREE_DEN": "05"}], "BIRD": [{"BIRD_ID": "50", "BIRD_ACT": "2", "BIRD_LOC": "4", "BIRD_DIS": "2"}, {"BIRD_ID": "74", "BIRD_ACT": "2", "BIRD_LOC": "4", "BIRD_DIS": "2"}, {"BIRD_ID": "39", "BIRD_ACT": "2", "BIRD_LOC": "4", "BIRD_DIS": "2"}, {"BIRD_ID": "12", "BIRD_ACT": "2", "BIRD_LOC": "4", "BIRD_DIS": "2"}, {"BIRD_ID": "47", "BIRD_ACT": "2", "BIRD_LOC": "4", "BIRD_DIS": "2"}, {"BIRD_ID": "65", "BIRD_ACT": "2", "BIRD_LOC": "4", "BIRD_DIS": "2"}, {"BIRD_ID": "69", "BIRD_ACT": "2", "BIRD_LOC": "4", "BIRD_DIS": "2"}], "MAMMAL": [{"MML_ID": "04", "MML_ACT": "4", "MML_LOC": "5", "MML_EVD": "4"}], "DO": "5.042", "PH": "7.605", "N3": "181.0", "N2": "16.26", "NH": "0.12", "PO": "0.679", "CH": "2.09", "HD": "150.6", "AK": "143.2", "SP": "N/A"}