{
  "AP": [
    "20",
    "20"
  ],
  "GTS": [
    "231",
    "231"
  ],
  "PG": [
    "1",
    "2"
  ],
  "LST": "0908",
  "CC": "9",
  "CT": "3",
  "PRECIP": "0",
  "WS": "0",
  "WD": "0",
  "LAND_HAB": "11",
  "WATER_HAB": "41",
  "SAT_HOG": "00",
  "SAT_SUN": "000",
  "SAT_SHA": "000",
  "SWT": [
    "000",
    "000"
  ],
  "HYPRO": [
    "000",
    "000",
    "000",
    "000",
    "000"
  ],
  "STSL": [
    "000",
    "000",
    "000",
    "000",
    "000",
    "000"
  ],
  "STSH": [
    "000",
    "000",
    "000",
    "000",
    "000",
    "000"
  ],
  "SCDT": "1",
  "CST": "2",
  "STK": "2",
  "RBN": "1",
  "SHN": "1",
  "TDS": [
    "000",
    "000"
  ],
  "TUR": [
    "000",
    "000"
  ],
  "ALB": [
    "00",
    "00",
    "00",
    "00",
    "00",
    "00",
    "00",
    "00",
    "00",
    "00"
  ],
  "DELTA": "00",
  "WCD": [
    "00",
    "00",
    "00",
    "00",
    "00",
    "00",
    "00",
    "00",
    "00",
    "00"
  ],
  "WCV": [
    "00",
    "00",
    "00",
    "00",
    "00",
    "00",
    "00",
    "00",
    "00",
    "00"
  ],
  "WIDTH": [
    "000",
    "000"
  ],
  "IMG": [
    "3246",
    "3245",
    "0093",
    "3238",
    "3240",
    "3244",
    "3239",
    "3243",
    "3237",
    "3255",
    "3256",
    "3250",
    "3253",
    "3252"
  ],
  "PAN_IMGS": "00",
  "JOB": [
    "6",
    "2",
    "8",
    "4",
    "1",
    "3",
    "7",
    "5",
    "9",
    "0"
  ],
  "ROCK": [
    {
      "SIM": "2",
      "AVG_SIZE": "06",
      "FW": "0",
      "FF": "0",
      "CVR": "0",
      "ERSN": "2",
      "SHP": "2",
      "B_FIELD": "00"
    },
    {
      "SIM": "3",
      "AVG_SIZE": "01",
      "FW": "0",
      "FF": "0",
      "CVR": "3",
      "ERSN": "2",
      "SHP": "2",
      "B_FIELD": "00"
    }
  ],
  "TREE": [
    {
      "TREE_ID": "43",
      "TREE_PCT": "2",
      "TREE_DIA": "25",
      "TREE_HT": "10",
      "TREE_DEN": "02"
    },
    {
      "TREE_ID": "46",
      "TREE_PCT": "2",
      "TREE_DIA": "74",
      "TREE_HT": "09",
      "TREE_DEN": "07"
    },
    {
      "TREE_ID": "49",
      "TREE_PCT": "2",
      "TREE_DIA": "10",
      "TREE_HT": "09",
      "TREE_DEN": "01"
    },
    {
      "TREE_ID": "39",
      "TREE_PCT": "2",
      "TREE_DIA": "29",
      "TREE_HT": "15",
      "TREE_DEN": "01"
    },
    {
      "TREE_ID": "48",
      "TREE_PCT": "2",
      "TREE_DIA": "08",
      "TREE_HT": "05",
      "TREE_DEN": "01"
    }
  ],
  "BIRD": [
    {
      "BIRD_ID": "47",
      "BIRD_ACT": "0",
      "BIRD_LOC": "0",
      "BIRD_DIS": "2"
    },
    {
      "BIRD_ID": "65",
      "BIRD_ACT": "0",
      "BIRD_LOC": "0",
      "BIRD_DIS": "2"
    },
    {
      "BIRD_ID": "69",
      "BIRD_ACT": "0",
      "BIRD_LOC": "0",
      "BIRD_DIS": "2"
    },
    {
      "BIRD_ID": "60",
      "BIRD_ACT": "0",
      "BIRD_LOC": "0",
      "BIRD_DIS": "2"
    }
  ],
  "MAMMAL": [],
  "DO": "6.565",
  "PH": "5.96",
  "N3": "21.12",
  "N2": "0.600",
  "NH": "1.484",
  "PO": "1.074",
  "CH": "0.116",
  "HD": "11.82",
  "AK": "16.08",
  "SP": "6.033"
}