{
  "AP": "95",
  "GTS": "331",
  "PG": "1",
  "LST": "4202",
  "CC": "2",
  "CT": "0",
  "PCP": "1",
  "WS": "1",
  "WD": "0",
  "LAND_HAB": "12",
  "WATER_HAB": "00",
  "SAT_HOG": "11",
  "SAT_SUN": "157",
  "SAT_SHA": "137",
  "SWT": [
    "000",
    "000"
  ],
  "HYPRO": [
    "000",
    "000",
    "000",
    "000",
    "000"
  ],
  "STSL": [
    "188",
    "187",
    "156",
    "126",
    "096",
    "086"
  ],
  "STSH": [
    "117",
    "089",
    "078",
    "075",
    "068",
    "060"
  ],
  "SCDT": "1",
  "CST": "3",
  "STK": "2",
  "RBN": "2",
  "SHN": "0",
  "TDS": [
    "000",
    "000"
  ],
  "TUR": [
    "000",
    "000"
  ],
  "ALB": [
    "90",
    "89",
    "89",
    "89",
    "89",
    "89",
    "89",
    "89",
    "89",
    "89"
  ],
  "DELTA_X": "00",
  "WCD": [
    "00",
    "00",
    "00",
    "00",
    "00",
    "00",
    "00",
    "00",
    "00",
    "00"
  ],
  "WCV": [
    "00",
    "00",
    "00",
    "00",
    "00",
    "00",
    "00",
    "00",
    "00",
    "00"
  ],
  "WIDTH": [
    "000",
    "000"
  ],
  "IMG": [
    "0492",
    "0491",
    "1473",
    "0000",
    "0000",
    "0486",
    "0000",
    "0000",
    "0487",
    "0000",
    "0000",
    "0488",
    "0000",
    "0000"
  ],
  "NUMBER_IN_PAN": "11",
  "JOB": [
    "5",
    "1",
    "4",
    "6",
    "2",
    "7",
    "1",
    "8",
    "1",
    "0"
  ],
  "ROCKS": {
    "SIM": "3",
    "AVG_SIZE": "34",
    "FW": "0",
    "FF": "0",
    "CVR": "3",
    "ERSN": "4",
    "SHP": "2",
    "B_FIELD": "04"
  },
  "TREES": [
    {
      "ID": "17",
      "PCT": "4",
      "DIA": "64",
      "HT": "21",
      "DENSITY": "08"
    },
    {
      "ID": "36",
      "PCT": "2",
      "DIA": "42",
      "HT": "12",
      "DENSITY": "12"
    },
    {
      "ID": "35",
      "PCT": "1",
      "DIA": "57",
      "HT": "19",
      "DENSITY": "00"
    }
  ],
  "BIRDS": [
    {
      "ID": "62",
      "ACT": "1",
      "LOC": "3",
      "DIS": "2"
    }
  ],
  "MAMMALS": [],
  "DO": "N/A",
  "PH": "N/A",
  "N3": "N/A",
  "N2": "N/A",
  "NH": "N/A",
  "PO": "N/A",
  "CH": "N/A",
  "HD": "N/A",
  "AK": "N/A",
  "SP": "N/A"
}