{
  "AP": "96",
  "GTS": "311",
  "PG": "1",
  "LST": "0051",
  "CC": "2",
  "CT": "0",
  "PRECIP": "1",
  "WS": "6",
  "WD": "0",
  "LAND_HAB": "44",
  "WATER_HAB": "00",
  "SAT_HOG": "70",
  "SAT_SUN": "000",
  "SAT_SHA": "095",
  "SWT": [
    "076",
    "075"
  ],
  "HYPRO": [
    "076",
    "000",
    "000",
    "000",
    "000"
  ],
  "STSL": [
    "000",
    "000",
    "000",
    "000",
    "000",
    "000"
  ],
  "STSH": [
    "090",
    "084",
    "071",
    "063",
    "055",
    "047"
  ],
  "SCDT": "1",
  "CST": "4",
  "STK": "3",
  "RBN": "3",
  "SHN": "2",
  "TDS": [
    "002",
    "003"
  ],
  "TUR": [
    "003",
    "004"
  ],
  "ALB": [
    "99",
    "99",
    "99",
    "99",
    "99",
    "99",
    "99",
    "99",
    "99",
    "99"
  ],
  "DELTA": "03",
  "WCD": [
    "02",
    "03",
    "05",
    "03",
    "02",
    "01",
    "01",
    "01",
    "01",
    "01"
  ],
  "WCV": [
    "08",
    "03",
    "06",
    "03",
    "08",
    "08",
    "11",
    "06",
    "11",
    "08"
  ],
  "WIDTH": [
    "370",
    "055"
  ],
  "IMG": [
    "0000",
    "0202",
    "0194",
    "0205",
    "0206",
    "0203",
    "0207",
    "0208",
    "0204",
    "0212",
    "0214",
    "0209",
    "0213",
    "0211"
  ],
  "PAN_IMGS": "08",
  "JOB": [
    "1",
    "7",
    "8",
    "1",
    "2",
    "5",
    "9",
    "4",
    "1",
    "0"
  ],
  "ROCK": {
    "SIM": "3",
    "AVG_SIZE": "80",
    "FW": "0",
    "FF": "0",
    "CVR": "1",
    "ERSN": "2",
    "SHP": "5",
    "B_FIELD": "04"
  },
  "TREE": [
    {
      "TREE_ID": "46",
      "TREE_PCT": "3",
      "TREE_DIA": "70",
      "TREE_HT": "29",
      "TREE_DEN": "10"
    },
    {
      "TREE_ID": "22",
      "TREE_PCT": "1",
      "TREE_DIA": "64",
      "TREE_HT": "28",
      "TREE_DEN": "05"
    },
    {
      "TREE_ID": "31",
      "TREE_PCT": "1",
      "TREE_DIA": "48",
      "TREE_HT": "20",
      "TREE_DEN": "30"
    }
  ],
  "BIRD": [],
  "MAMMAL": [
    {
      "MML_ID": "08",
      "MML_ACT": "3",
      "MML_LOC": "3",
      "MML_EVD": "0"
    },
    {
      "MML_ID": "07",
      "MML_ACT": "3",
      "MML_LOC": "3",
      "MML_EVD": "0"
    },
    {
      "MML_ID": "09",
      "MML_ACT": "3",
      "MML_LOC": "3",
      "MML_EVD": "0"
    },
    {
      "MML_ID": "22",
      "MML_ACT": "3",
      "MML_LOC": "3",
      "MML_EVD": "0"
    },
    {
      "MML_ID": "16",
      "MML_ACT": "3",
      "MML_LOC": "3",
      "MML_EVD": "0"
    }
  ],
  "DO": "11.03",
  "PH": "7.250",
  "N3": "5.90",
  "N2": "0.21",
  "NH": "N/A",
  "PO": "3.87",
  "CH": "0.03",
  "HD": "7.41",
  "AK": "19.38",
  "SP": "N/A"
}